{
  "project_info": {
    "project_number": "1030099176575",
    "project_id": "dna-digitaliza-test",
    "storage_bucket": "dna-digitaliza-test.appspot.com"
  },
  "client": [
    {
      "client_info": {
        "mobilesdk_app_id": "1:1030099176575:android:1668e609199ccaabb5834a",
        "android_client_info": {
          "package_name": "com.romulodna"
        }
      },
      "oauth_client": [
        {
          "client_id": "1030099176575-4it5gdk0gu9106uf5rlbld325lmboe4u.apps.googleusercontent.com",
          "client_type": 3
        }
      ],
      "api_key": [
        {
          "current_key": "AIzaSyD2Wjg1Hpxyt_LkmJEKzNjurW4rPItxhOI"
        }
      ],
      "services": {
        "appinvite_service": {
          "other_platform_oauth_client": [
            {
              "client_id": "1030099176575-4it5gdk0gu9106uf5rlbld325lmboe4u.apps.googleusercontent.com",
              "client_type": 3
            }
          ]
        }
      }
    }
  ],
  "configuration_version": "1"
}